CHANGES.txt
MANIFEST.in
README.rst
development.ini
production.ini
setup.cfg
setup.py
kotti_splashpage/__init__.py
kotti_splashpage/tests.py
kotti_splashpage.egg-info/PKG-INFO
kotti_splashpage.egg-info/SOURCES.txt
kotti_splashpage.egg-info/dependency_links.txt
kotti_splashpage.egg-info/entry_points.txt
kotti_splashpage.egg-info/not-zip-safe
kotti_splashpage.egg-info/requires.txt
kotti_splashpage.egg-info/top_level.txt
kotti_splashpage/templates/splash-page.pt