Metadata-Version: 1.1
Name: kotti-splashpage
Version: 0.2.0
Summary:       kotti_splashpage is a kotti package to setup the home page as a splash
Home-page: http://github.com/koansys/kotti_splashpage
Author: Koansys, LLC and contributors
Author-email: info@koansys.com
License: UNKNOWN
Keywords: web pyramid pylons
Platform: UNKNOWN
Classifier: Programming Language :: Python
Classifier: Framework :: Pyramid
Classifier: Topic :: Internet :: WWW/HTTP
Classifier: Topic :: Internet :: WWW/HTTP :: WSGI :: Application
